teneto/__init__.py
teneto/_version.py
teneto/classes/__init__.py
teneto/classes/bids.py
teneto/classes/bids_new.py
teneto/classes/network.py
teneto/classes/preproc.py
teneto/classes/workflow.py
teneto/communitydetection/__init__.py
teneto/communitydetection/louvain.py
teneto/communitydetection/louvain_old.py
teneto/communitydetection/tctc.py
teneto/communitydetection/tctc_opt_bu.py
teneto/communitydetection/trajectoryclustering.py
teneto/communitydetection/optimization/__init__.py
teneto/communitydetection/optimization/multilayer_louvain.py
teneto/communitydetection/optimization/simulated_annealing.py
teneto/communitydetection/static/__init__.py
teneto/communitydetection/static/modularity_based_clustering.py
teneto/communitymeasures/__init__.py
teneto/communitymeasures/allegiance.py
teneto/communitymeasures/flexibility.py
teneto/communitymeasures/integration.py
teneto/communitymeasures/persistence.py
teneto/communitymeasures/promiscuity.py
teneto/communitymeasures/recruitment.py
teneto/config/tenetobids/tenetobids.json
teneto/config/tenetobids/tenetobids_description.json
teneto/config/tenetobids/tenetobids_structure.json
teneto/data/testdata/dummybids/dataset_description.json
teneto/data/testdata/dummybids/participants.tsv
teneto/data/testdata/dummybids/derivatives/fmriprep/dataset_description.json
teneto/data/testdata/dummybids/derivatives/fmriprep/sub-001/func/sub-001_task-a_run-1_desc-confounds_regressors.tsv
teneto/data/testdata/dummybids/derivatives/fmriprep/sub-001/func/sub-001_task-a_run-1_desc-preproc_bold.nii.gz
teneto/data/testdata/dummybids/derivatives/fmriprep/sub-001/func/sub-001_task-a_run-2_desc-confounds_regressors.tsv
teneto/data/testdata/dummybids/derivatives/fmriprep/sub-001/func/sub-001_task-a_run-2_desc-preproc_bold.nii.gz
teneto/data/testdata/dummybids/derivatives/fmriprep/sub-001/func/sub-001_task-b_run-1_desc-confounds_regressors.tsv
teneto-0.5.3.dist-info/LICENSE
teneto-0.5.3.dist-info/METADATA
teneto-0.5.3.dist-info/WHEEL
teneto-0.5.3.dist-info/entry_points.txt
teneto-0.5.3.dist-info/top_level.txt
teneto-0.5.3.dist-info/RECORD
