Metadata-Version: 2.1
Name: teneto
Version: 0.5.3
Summary: Temporal network tools
Home-page: https://www.github.com/wiheto/teneto
Author: William Hedley Thompson
Author-email: hedley@startmail.com
License: UNKNOWN
Download-URL: https://github.com/wiheto/teneto/archive/0.3.3.tar.gz
Platform: UNKNOWN
Requires-Python: >3.5
Requires-Dist: nilearn (>=0.6.0)
Requires-Dist: pybids (>=0.11.1)
Requires-Dist: statsmodels (>=0.8.0)
Requires-Dist: networkx (>=2.0)
Requires-Dist: python-louvain (>=0.13)
Requires-Dist: pandas (>=0.21)
Requires-Dist: scipy (>=1.4.1)
Requires-Dist: numpy (>=1.19.5)
Requires-Dist: templateflow (>=0.6.2)
